Workbook

Sheet 見積単価
A1: 2026年10月5日付 御見積書（ミツヤ産業㈱ 福山営業所 御中）の単価
A2: 出典：お客様提供の見積書PDF（2ページ）。単価は税別。
A4: No | B4: 品名 | C4: 単位 | D4: 改定前単価（～2026/10/20） | E4: 改定後単価（2026/10/21～） | F4: 備考
A5: 1 | B5: BP-130LiⅢα 本体のみ | C5: 台 | D5: 131000 | E5: 144000
A6: 2 | B6: BP-130LiⅢα用パッド台 | C6: 枚 | D6: 14200 | E6: 15200
A7: 3 | B7: BP-130LiⅢα用タンク | C7: 個 | D7: 22000 | E7: 23550
A8: 4 | B8: 充電器 CLQ-1N | C8: 台 | D8: 43300 | E8: 45500
A9: 5 | B9: バッテリーLV14MX 14Ah | C9: 個 | D9: 83000 | E9: 87100 | F9: 使用目安100min
A10: 6 | B10: バッテリーLV925MX | C10: 個 | D10: 63000 | E10: 66100 | F10: 使用目安75min
A11: 7 | B11: コンポジットパッド13インチ シルバー | C11: 枚 | D11: 3000 | E11: 3000 | F11: 軽汚染用
A12: 8 | B12: コンポジットパッド13インチ ゴールド | C12: 枚 | D12: 3000 | E12: 3000 | F12: 重汚染用
A13: 9 | B13: ナイロンブラシ13インチ用 | C13: 枚 | D13: 18900 | E13: 20690
A15: 単価を変更する場合はこのシートの青字を書き換えると、注文書・請求書に反映されます。

Sheet 注文書
A1: 注 文 書
F2: 注文番号
A3: 有限会社フクショウ 御中 | F3: 注文日
A4: 〒721-0974 福山市東深津町3丁目11番23号
A5: TEL 084-923-9521 / FAX 084-923-9520 | E5: 発注者
E6: ミツヤ産業株式会社 福山営業所
A7: 下記の通り注文いたします。 | E7: 住所
A8: （2026年10月5日付 御見積書に基づく） | E8: TEL
E9: 担当者
B10: 納入場所 | C10: 貴社 | G10: 印
B11: 納期
B12: 支払条件
B13: 適用価格 | C13: 改定前（～2026/10/20） | F13: 合計（税込） | G13: =F29 -> 419540 | I13: 0.1 | J13: ← 消費税率
A15: No | B15: 品名 | C15: 数量 | D15: 単位 | E15: 単価 | F15: 金額 | G15: 備考
A16: 1 | B16: =見積単価!B5 -> BP-130LiⅢα 本体のみ | C16: 1 | D16: =見積単価!C5 -> 台 | E16: =IF($C$13="改定後（2026/10/21～）",見積単価!E5,見積単価!D5) -> 131000 | F16: =IF(C16="","",C16*E16) -> 131000 | G16: =IF(見積単価!F5="","",見積単価!F5)
A17: 2 | B17: =見積単価!B6 -> BP-130LiⅢα用パッド台 | C17: 1 | D17: =見積単価!C6 -> 枚 | E17: =IF($C$13="改定後（2026/10/21～）",見積単価!E6,見積単価!D6) -> 14200 | F17: =IF(C17="","",C17*E17) -> 14200 | G17: =IF(見積単価!F6="","",見積単価!F6)
A18: 3 | B18: =見積単価!B7 -> BP-130LiⅢα用タンク | C18: 1 | D18: =見積単価!C7 -> 個 | E18: =IF($C$13="改定後（2026/10/21～）",見積単価!E7,見積単価!D7) -> 22000 | F18: =IF(C18="","",C18*E18) -> 22000 | G18: =IF(見積単価!F7="","",見積単価!F7)
A19: 4 | B19: =見積単価!B8 -> 充電器 CLQ-1N | C19: 1 | D19: =見積単価!C8 -> 台 | E19: =IF($C$13="改定後（2026/10/21～）",見積単価!E8,見積単価!D8) -> 43300 | F19: =IF(C19="","",C19*E19) -> 43300 | G19: =IF(見積単価!F8="","",見積単価!F8)
A20: 5 | B20: =見積単価!B9 -> バッテリーLV14MX 14Ah | C20: 1 | D20: =見積単価!C9 -> 個 | E20: =IF($C$13="改定後（2026/10/21～）",見積単価!E9,見積単価!D9) -> 83000 | F20: =IF(C20="","",C20*E20) -> 83000 | G20: =IF(見積単価!F9="","",見積単価!F9) -> 使用目安100min
A21: 6 | B21: =見積単価!B10 -> バッテリーLV925MX | C21: 1 | D21: =見積単価!C10 -> 個 | E21: =IF($C$13="改定後（2026/10/21～）",見積単価!E10,見積単価!D10) -> 63000 | F21: =IF(C21="","",C21*E21) -> 63000 | G21: =IF(見積単価!F10="","",見積単価!F10) -> 使用目安75min
A22: 7 | B22: =見積単価!B11 -> コンポジットパッド13インチ シルバー | C22: 1 | D22: =見積単価!C11 -> 枚 | E22: =IF($C$13="改定後（2026/10/21～）",見積単価!E11,見積単価!D11) -> 3000 | F22: =IF(C22="","",C22*E22) -> 3000 | G22: =IF(見積単価!F11="","",見積単価!F11) -> 軽汚染用
A23: 8 | B23: =見積単価!B12 -> コンポジットパッド13インチ ゴールド | C23: 1 | D23: =見積単価!C12 -> 枚 | E23: =IF($C$13="改定後（2026/10/21～）",見積単価!E12,見積単価!D12) -> 3000 | F23: =IF(C23="","",C23*E23) -> 3000 | G23: =IF(見積単価!F12="","",見積単価!F12) -> 重汚染用
A24: 9 | B24: =見積単価!B13 -> ナイロンブラシ13インチ用 | C24: 1 | D24: =見積単価!C13 -> 枚 | E24: =IF($C$13="改定後（2026/10/21～）",見積単価!E13,見積単価!D13) -> 18900 | F24: =IF(C24="","",C24*E24) -> 18900 | G24: =IF(見積単価!F13="","",見積単価!F13)
D27: 小計（税別） | F27: =SUM(F16:F26) -> 381400
D28: 消費税（10%対象） | F28: =ROUNDDOWN(F27*$I$13,0) -> 38140
D29: 合計（税込） | F29: =F27+F28 -> 419540
A31: 備考：
A35: 【記入方法】黄色のセル（注文番号・注文日・住所等・納期・支払条件・数量・適用価格）を記入してください。不要な品目は数量を空欄にすると金額が空欄になります。

Sheet 請求書
A1: 請 求 書
F2: 請求番号
A3: ミツヤ産業株式会社 福山営業所 御中 | F3: 請求日
A5: 下記の通りご請求申し上げます。 | E5: 〒721-0974
A6: ="ご注文番号："&注文書!G2 -> ご注文番号： | E6: 福山市東深津町3丁目11番23号
E7: 有限会社フクショウ
E8: 取締役 羽原 英明
A9: ご請求金額（税込） | E9: TEL 084-923-9521 / FAX 084-923-9520
A10: =F29 -> 419540 | E10: 登録番号 | F10: T
G11: 印
B12: お支払期限
B13: 取引年月日（納品日） | I13: =注文書!I13 -> 0.1 | J13: ← 消費税率（注文書と連動）
A15: No | B15: 品名 | C15: 数量 | D15: 単位 | E15: 単価 | F15: 金額 | G15: 備考
A16: 1 | B16: =IF(注文書!B16="","",注文書!B16) -> BP-130LiⅢα 本体のみ | C16: =IF(注文書!C16="","",注文書!C16) -> 1 | D16: =IF(注文書!D16="","",注文書!D16) -> 台 | E16: =IF(注文書!E16="","",注文書!E16) -> 131000 | F16: =IF(OR(C16="",E16=""),"",C16*E16) -> 131000 | G16: =IF(注文書!G16="","",注文書!G16)
A17: 2 | B17: =IF(注文書!B17="","",注文書!B17) -> BP-130LiⅢα用パッド台 | C17: =IF(注文書!C17="","",注文書!C17) -> 1 | D17: =IF(注文書!D17="","",注文書!D17) -> 枚 | E17: =IF(注文書!E17="","",注文書!E17) -> 14200 | F17: =IF(OR(C17="",E17=""),"",C17*E17) -> 14200 | G17: =IF(注文書!G17="","",注文書!G17)
A18: 3 | B18: =IF(注文書!B18="","",注文書!B18) -> BP-130LiⅢα用タンク | C18: =IF(注文書!C18="","",注文書!C18) -> 1 | D18: =IF(注文書!D18="","",注文書!D18) -> 個 | E18: =IF(注文書!E18="","",注文書!E18) -> 22000 | F18: =IF(OR(C18="",E18=""),"",C18*E18) -> 22000 | G18: =IF(注文書!G18="","",注文書!G18)
A19: 4 | B19: =IF(注文書!B19="","",注文書!B19) -> 充電器 CLQ-1N | C19: =IF(注文書!C19="","",注文書!C19) -> 1 | D19: =IF(注文書!D19="","",注文書!D19) -> 台 | E19: =IF(注文書!E19="","",注文書!E19) -> 43300 | F19: =IF(OR(C19="",E19=""),"",C19*E19) -> 43300 | G19: =IF(注文書!G19="","",注文書!G19)
A20: 5 | B20: =IF(注文書!B20="","",注文書!B20) -> バッテリーLV14MX 14Ah | C20: =IF(注文書!C20="","",注文書!C20) -> 1 | D20: =IF(注文書!D20="","",注文書!D20) -> 個 | E20: =IF(注文書!E20="","",注文書!E20) -> 83000 | F20: =IF(OR(C20="",E20=""),"",C20*E20) -> 83000 | G20: =IF(注文書!G20="","",注文書!G20) -> 使用目安100min
A21: 6 | B21: =IF(注文書!B21="","",注文書!B21) -> バッテリーLV925MX | C21: =IF(注文書!C21="","",注文書!C21) -> 1 | D21: =IF(注文書!D21="","",注文書!D21) -> 個 | E21: =IF(注文書!E21="","",注文書!E21) -> 63000 | F21: =IF(OR(C21="",E21=""),"",C21*E21) -> 63000 | G21: =IF(注文書!G21="","",注文書!G21) -> 使用目安75min
A22: 7 | B22: =IF(注文書!B22="","",注文書!B22) -> コンポジットパッド13インチ シルバー | C22: =IF(注文書!C22="","",注文書!C22) -> 1 | D22: =IF(注文書!D22="","",注文書!D22) -> 枚 | E22: =IF(注文書!E22="","",注文書!E22) -> 3000 | F22: =IF(OR(C22="",E22=""),"",C22*E22) -> 3000 | G22: =IF(注文書!G22="","",注文書!G22) -> 軽汚染用
A23: 8 | B23: =IF(注文書!B23="","",注文書!B23) -> コンポジットパッド13インチ ゴールド | C23: =IF(注文書!C23="","",注文書!C23) -> 1 | D23: =IF(注文書!D23="","",注文書!D23) -> 枚 | E23: =IF(注文書!E23="","",注文書!E23) -> 3000 | F23: =IF(OR(C23="",E23=""),"",C23*E23) -> 3000 | G23: =IF(注文書!G23="","",注文書!G23) -> 重汚染用
A24: 9 | B24: =IF(注文書!B24="","",注文書!B24) -> ナイロンブラシ13インチ用 | C24: =IF(注文書!C24="","",注文書!C24) -> 1 | D24: =IF(注文書!D24="","",注文書!D24) -> 枚 | E24: =IF(注文書!E24="","",注文書!E24) -> 18900 | F24: =IF(OR(C24="",E24=""),"",C24*E24) -> 18900 | G24: =IF(注文書!G24="","",注文書!G24)
D27: 小計（税別） | F27: =SUM(F16:F26) -> 381400
D28: 消費税（10%対象） | F28: =ROUNDDOWN(F27*$I$13,0) -> 38140
D29: 合計（税込） | F29: =F27+F28 -> 419540
A31: お振込先
B32: 金融機関・支店
B33: 口座種別・番号
B34: 口座名義
A36: ※振込手数料は貴社にてご負担くださいますようお願い申し上げます。
A37: 【記入方法】黄色のセル（請求番号・請求日・登録番号・支払期限・取引年月日・振込先）を記入してください。明細は「注文書」シートから自動で転記されます。
